superfluid/__init__.py
superfluid/src/__init__.py
superfluid/src/abis.py
superfluid/src/cfa.py
superfluid/src/constants.py
superfluid/src/errors.py
superfluid/src/host.py
superfluid/src/metadata.py
superfluid/src/operation.py
superfluid/src/types.py
superfluid/src/utils.py
superfluid/test/__init__.py
superfluid/test/test_utils.py
superfluid-0.2.1.dist-info/LICENSE.txt
superfluid-0.2.1.dist-info/METADATA
superfluid-0.2.1.dist-info/WHEEL
superfluid-0.2.1.dist-info/top_level.txt
superfluid-0.2.1.dist-info/RECORD
