Metadata-Version: 2.1
Name: superfluid
Version: 0.2.1
Summary: Python SDK for the Superfluid Protocol
Home-page: https://github.com/Godspower-Eze/superfluid.py
Author: Godspower-Eze
Author-email: Godspowereze260@gmail.com
License: MIT
Classifier: License :: OSI Approved :: MIT License
Classifier: Programming Language :: Python :: 3
Classifier: Operating System :: OS Independent
Requires-Python: >=3
License-File: LICENSE.txt
Requires-Dist: web3 (==6.3.0)
Requires-Dist: python-decouple (==3.8)
Provides-Extra: dev
Requires-Dist: twine (>=4.0.2) ; extra == 'dev'
